langchain_caai/__init__.py
langchain_caai/caai_emb_client.py
langchain_caai-0.4.dist-info/LICENSE.txt
langchain_caai-0.4.dist-info/METADATA
langchain_caai-0.4.dist-info/WHEEL
langchain_caai-0.4.dist-info/top_level.txt
langchain_caai-0.4.dist-info/RECORD
